{
  "publicPath": "https://static.xiaohuochai.site/client/",
  "all": [
    "static/css/app.9619d1b401a38401676e768e734847c9.css",
    "static/img/react-big.282e404.jpg",
    "static/img/match-bg.0f9a8d7.jpg",
    "static/js/vendor-async.8e122223ecd9f2e45718.js",
    "static/js/auth.f3fb894c1e9a4964a030.js",
    "static/js/comment.0eaf2710874caf5251fe.js",
    "static/js/category.b7e1a86b4ec9f046db18.js",
    "static/js/home.05049fa016e71f18dc56.js",
    "static/js/postlist.de62b11d1c76f33342bc.js",
    "static/js/commentlist.f4c2b01e1af788c14ad7.js",
    "static/js/post.96dc38b5f28aefa9c5fb.js",
    "static/js/categorylist.3145fb47c34d17ef9b77.js",
    "static/js/user.4f83202362d7aafdb2c0.js",
    "static/js/vendor.0741683f2f1e5de8c1a8.js",
    "static/js/app.cca0c34d525fe52c8146.js",
    "static/js/manifest.6ca449ca4a9df1ffcf23.js",
    "static/img/vue-big.172586f.jpg",
    "static/css/app.9619d1b401a38401676e768e734847c9.css.map",
    "static/js/vendor-async.8e122223ecd9f2e45718.js.map",
    "static/js/auth.f3fb894c1e9a4964a030.js.map",
    "static/js/comment.0eaf2710874caf5251fe.js.map",
    "static/js/category.b7e1a86b4ec9f046db18.js.map",
    "static/js/home.05049fa016e71f18dc56.js.map",
    "static/js/postlist.de62b11d1c76f33342bc.js.map",
    "static/js/commentlist.f4c2b01e1af788c14ad7.js.map",
    "static/js/post.96dc38b5f28aefa9c5fb.js.map",
    "static/js/categorylist.3145fb47c34d17ef9b77.js.map",
    "static/js/user.4f83202362d7aafdb2c0.js.map",
    "static/js/vendor.0741683f2f1e5de8c1a8.js.map",
    "static/js/app.cca0c34d525fe52c8146.js.map",
    "static/js/manifest.6ca449ca4a9df1ffcf23.js.map",
    "static/favicon.ico"
  ],
  "initial": [
    "static/js/manifest.6ca449ca4a9df1ffcf23.js",
    "static/js/vendor.0741683f2f1e5de8c1a8.js",
    "static/js/app.cca0c34d525fe52c8146.js"
  ],
  "async": [
    "static/js/vendor-async.8e122223ecd9f2e45718.js",
    "static/js/auth.f3fb894c1e9a4964a030.js",
    "static/js/comment.0eaf2710874caf5251fe.js",
    "static/js/category.b7e1a86b4ec9f046db18.js",
    "static/js/home.05049fa016e71f18dc56.js",
    "static/js/postlist.de62b11d1c76f33342bc.js",
    "static/js/commentlist.f4c2b01e1af788c14ad7.js",
    "static/js/post.96dc38b5f28aefa9c5fb.js",
    "static/js/categorylist.3145fb47c34d17ef9b77.js",
    "static/js/user.4f83202362d7aafdb2c0.js"
  ],
  "modules": {
    "58903376": [
      13,
      28
    ],
    "59310697": [
      13,
      28
    ],
    "90241432": [
      13,
      28
    ],
    "6846b51a": [
      6,
      21
    ],
    "19e9ddfb": [
      10,
      25
    ],
    "edd18d5e": [
      3,
      18
    ],
    "db7bfb6a": [
      8,
      23
    ],
    "52cfb800": [
      3,
      18
    ],
    "4204cd62": [
      13,
      28
    ],
    "102d1790": [
      13,
      28
    ],
    "d0fecc74": [
      7,
      22,
      1,
      16,
      2
    ],
    "0f064c7b": [
      4,
      19
    ],
    "4c6fd146": [
      13,
      28
    ],
    "2f0c12f3": [
      14,
      0,
      29
    ],
    "513d1d58": [
      13,
      28
    ],
    "8d7fcf62": [
      13,
      28
    ],
    "c9f17516": [
      13,
      28
    ],
    "3afa80d4": [
      10,
      25
    ],
    "3606ce91": [
      13,
      28
    ],
    "2f7f05ef": [
      13,
      28
    ],
    "1d9c4c2a": [
      13,
      28
    ],
    "d7a4a262": [
      13,
      28
    ],
    "643b8161": [
      14,
      0,
      29
    ],
    "a5946902": [
      13,
      28
    ],
    "57f261d6": [
      11,
      26
    ],
    "0b9c567e": [
      13,
      28
    ],
    "0e2d7442": [
      5,
      20
    ],
    "267fb7c5": [
      13,
      28
    ],
    "12e3f49a": [
      13,
      28
    ],
    "7af5403e": [
      13,
      28
    ],
    "55f3d176": [
      13,
      28
    ],
    "d8e8e390": [
      8,
      23
    ],
    "ff95a826": [
      5,
      20
    ],
    "d362438e": [
      13,
      28
    ],
    "267d5d48": [
      13,
      28
    ],
    "3e4a3e38": [
      13,
      28
    ],
    "25af6596": [
      14,
      0,
      29
    ],
    "4b2bc5d0": [
      13,
      28
    ],
    "62557d6c": [
      13,
      28
    ],
    "7596acfe": [
      13,
      28
    ],
    "256fb727": [
      4,
      19
    ],
    "39a0d604": [
      13,
      28
    ],
    "0d6675e0": [
      7,
      22,
      1,
      16,
      2
    ],
    "4f920441": [
      13,
      28
    ],
    "e13641be": [
      13,
      28
    ],
    "18212e96": [
      13,
      28
    ],
    "90289fe8": [
      13,
      28
    ],
    "7c54f4b1": [
      6,
      21
    ],
    "7813bdb4": [
      13,
      28
    ],
    "bc6d9dae": [
      13,
      28
    ],
    "42345e62": [
      13,
      28
    ],
    "944c7f72": [
      7,
      22,
      1,
      16,
      2
    ],
    "420614cb": [
      13,
      28
    ],
    "f7b9f372": [
      13,
      28
    ],
    "3520748b": [
      13,
      28
    ],
    "6d2e1ff0": [
      13,
      28
    ],
    "5a92c926": [
      13,
      28
    ],
    "4223eeae": [
      13,
      28
    ],
    "09b42a99": [
      6,
      21
    ],
    "b40976c0": [
      7,
      22,
      1,
      16,
      2
    ],
    "232a8b2a": [
      14,
      0,
      29
    ],
    "063d18e0": [
      13,
      28
    ],
    "6fbcdb25": [
      4,
      19
    ],
    "372e1eda": [
      13,
      28
    ],
    "4a5cb929": [
      13,
      28
    ],
    "f7669406": [
      7,
      22,
      1,
      16,
      2
    ],
    "b080b844": [
      4,
      19
    ],
    "2af884a3": [
      13,
      28
    ],
    "1b34a8bf": [
      13,
      28
    ],
    "19a8e147": [
      13,
      28
    ],
    "1847b4dd": [
      5,
      20
    ],
    "6095b07e": [
      14,
      0,
      29
    ],
    "540ae33a": [
      4,
      19
    ],
    "5a8959dd": [
      13,
      28
    ],
    "6e96e2d8": [
      14,
      0,
      29
    ],
    "2f7f4468": [
      13,
      28
    ],
    "1b62e25c": [
      14,
      0,
      29
    ],
    "16b2fd99": [
      13,
      28
    ],
    "3576bd98": [
      13,
      28
    ],
    "27470c64": [
      7,
      22,
      1,
      16,
      2
    ],
    "35c0067a": [
      13,
      28
    ],
    "7e3c5fb2": [
      13,
      28
    ],
    "3ec4a1b4": [
      13,
      28
    ],
    "16dded08": [
      3,
      18
    ],
    "567e3fae": [
      13,
      28
    ],
    "37be50ce": [
      13,
      28
    ],
    "4a29bb4c": [
      4,
      19
    ],
    "8fe75dfc": [
      5,
      20
    ],
    "808806ee": [
      13,
      28
    ],
    "8653a19c": [
      13,
      28
    ],
    "1ca2a248": [
      7,
      22,
      1,
      16,
      2
    ],
    "8cc9ab2c": [
      13,
      28
    ],
    "29c4f5ea": [
      13,
      28
    ],
    "bf6f931e": [
      4,
      19
    ],
    "2d811230": [
      3,
      18
    ],
    "41022b70": [
      13,
      28
    ],
    "5679f0f8": [
      7,
      22,
      1,
      16,
      2
    ],
    "0ef35366": [
      13,
      28
    ],
    "a6ad870c": [
      14,
      0,
      29
    ],
    "bbbd4e88": [
      14,
      0,
      29
    ],
    "9031b754": [
      13,
      28
    ],
    "0dfe7267": [
      3,
      18
    ],
    "76a5fd0f": [
      13,
      28
    ],
    "33b93a50": [
      13,
      28
    ],
    "13ea85e3": [
      13,
      28
    ],
    "73a14027": [
      13,
      28
    ],
    "358b42c6": [
      5,
      20
    ],
    "4230ace2": [
      14,
      0,
      29
    ],
    "77a8ec0d": [
      13,
      28
    ],
    "6bf9f950": [
      13,
      28
    ],
    "15356afa": [
      13,
      28
    ],
    "683c4437": [
      13,
      28
    ],
    "ec351fd2": [
      10,
      25
    ],
    "e5b0f08e": [
      4,
      19
    ],
    "072a7886": [
      13,
      28
    ],
    "a70007bc": [
      13,
      28
    ],
    "91c2e44a": [
      9,
      24
    ],
    "75e5130f": [
      3,
      18
    ],
    "752ea646": [
      7,
      22,
      1,
      16,
      2
    ],
    "179b8c21": [
      9,
      24
    ],
    "297db0f2": [
      13,
      28
    ],
    "936d77de": [
      13,
      28
    ],
    "253fdbb1": [
      3,
      18
    ],
    "2759a1a7": [
      14,
      0,
      29
    ],
    "1d299f37": [
      13,
      28
    ],
    "67d77f86": [
      13,
      28
    ],
    "6b3b44db": [
      14,
      0,
      29
    ],
    "07791cb9": [
      13,
      28
    ],
    "60c583ca": [
      13,
      28
    ],
    "9e30c182": [
      4,
      19
    ],
    "6784a0d0": [
      13,
      28
    ],
    "1c4ce464": [
      14,
      0,
      29
    ],
    "185281e3": [
      13,
      28
    ],
    "9209cbf2": [
      13,
      28
    ],
    "6bac09b0": [
      13,
      28
    ],
    "372baa35": [
      13,
      28
    ],
    "1b4c1cca": [
      13,
      28
    ],
    "22ecba62": [
      4,
      19
    ],
    "eded9134": [
      13,
      28
    ],
    "9987664c": [
      13,
      28
    ],
    "dc882fde": [
      13,
      28
    ],
    "0c9b4e46": [
      13,
      28
    ],
    "3496f357": [
      13,
      28
    ],
    "931ff0d4": [
      13,
      28
    ],
    "473ac768": [
      13,
      28
    ],
    "27fa9ab7": [
      4,
      19
    ],
    "2e2ee78e": [
      12,
      27
    ],
    "7ffa3525": [
      13,
      28
    ],
    "2918efc1": [
      13,
      28
    ],
    "8c5a04e8": [
      13,
      28
    ],
    "0bd56514": [
      13,
      28
    ],
    "05ef1eaa": [
      12,
      27
    ],
    "20ac257a": [
      13,
      28
    ],
    "05bd783a": [
      7,
      22,
      1,
      16,
      2
    ],
    "5a887edb": [
      14,
      0,
      29
    ],
    "7e5a7015": [
      13,
      28
    ],
    "b1586d34": [
      13,
      28
    ],
    "fb3f4b50": [
      7,
      22,
      1,
      16,
      2
    ],
    "53737b15": [
      13,
      28
    ],
    "9f96f8da": [
      13,
      28
    ],
    "476f1728": [
      10,
      25
    ],
    "2a30a531": [
      3,
      18
    ],
    "0c6662fe": [
      4,
      19
    ],
    "7312b2f5": [
      14,
      0,
      29
    ],
    "585ae4d7": [
      13,
      28
    ],
    "0feb74e0": [
      13,
      28
    ],
    "4b5a3a0d": [
      13,
      28
    ],
    "6af768e5": [
      13,
      28
    ],
    "01292b16": [
      4,
      19
    ],
    "7756204f": [
      14,
      0,
      29
    ],
    "7e1f9e22": [
      4,
      19
    ],
    "3122a36c": [
      9,
      24
    ],
    "2cc43acf": [
      13,
      28
    ],
    "70b82496": [
      13,
      28
    ],
    "2ab3f99a": [
      14,
      0,
      29
    ],
    "676aaff8": [
      6,
      21
    ],
    "69887d0a": [
      4,
      19
    ],
    "09f7fc18": [
      13,
      28
    ],
    "1d83f3d3": [
      13,
      28
    ],
    "a215e380": [
      13,
      28
    ],
    "3d1750ad": [
      13,
      28
    ],
    "0403e324": [
      13,
      28
    ],
    "23e2ef5b": [
      13,
      28
    ],
    "4591ed7a": [
      13,
      28
    ],
    "d466e09e": [
      13,
      28
    ],
    "493a52b5": [
      13,
      28
    ],
    "44c0ad66": [
      13,
      28
    ],
    "246524fe": [
      13,
      28
    ],
    "7b845dd8": [
      13,
      28
    ],
    "76913bd2": [
      13,
      28
    ],
    "e622853a": [
      4,
      19
    ],
    "4dcf76a2": [
      13,
      28
    ],
    "f9a433c2": [
      14,
      0,
      29
    ],
    "5b3ddadf": [
      4,
      19
    ],
    "71e0ac58": [
      5,
      20
    ],
    "258c3df0": [
      13,
      28
    ],
    "a8965fcc": [
      5,
      20
    ],
    "59dc25ee": [
      11,
      26
    ],
    "eae12210": [
      13,
      28
    ],
    "71472ad7": [
      13,
      28
    ],
    "359bccec": [
      14,
      0,
      29
    ],
    "6577d117": [
      13,
      28
    ],
    "239cabaa": [
      13,
      28
    ],
    "70d3a692": [
      13,
      28
    ],
    "2afe64cb": [
      13,
      28
    ],
    "8da5186a": [
      14,
      0,
      29
    ],
    "7b18c22c": [
      9,
      24
    ],
    "9c5c59d2": [
      14,
      0,
      29
    ],
    "6f34ad74": [
      13,
      28
    ],
    "4ab7cc94": [
      13,
      28
    ],
    "8904d448": [
      13,
      28
    ],
    "6c376eba": [
      13,
      28
    ],
    "f6a2962a": [
      13,
      28
    ],
    "4c602786": [
      14,
      0,
      29
    ],
    "3eff3999": [
      4,
      19
    ],
    "ffbb91f4": [
      3,
      18
    ],
    "243f13c4": [
      8,
      23
    ],
    "494db330": [
      13,
      28
    ],
    "52a3d2de": [
      7,
      22,
      1,
      16,
      2
    ],
    "808321f2": [
      13,
      28
    ],
    "844a2ca2": [
      7,
      22,
      1,
      16,
      2
    ],
    "53bd5a28": [
      13,
      28
    ],
    "533ae044": [
      13,
      28
    ],
    "9555cd52": [
      4,
      19
    ],
    "a7803876": [
      4,
      19
    ],
    "04bfdd6c": [
      7,
      22,
      1,
      16,
      2
    ],
    "4ae29bca": [
      4,
      19
    ],
    "f9306e2e": [
      3,
      18
    ],
    "4eb6837b": [
      14,
      0,
      29
    ],
    "ae47ec08": [
      13,
      28
    ],
    "cd4971ce": [
      13,
      28
    ],
    "51d1d494": [
      14,
      0,
      29
    ],
    "a8f37502": [
      13,
      28
    ],
    "3318b990": [
      13,
      28
    ],
    "8767d532": [
      13,
      28
    ],
    "0efdfc48": [
      14,
      0,
      29
    ],
    "20186a30": [
      13,
      28
    ]
  }
}